hsm_nibble/__init__.py
hsm_nibble/debug.py
hsm_nibble/dxf.py
hsm_nibble/geometry.py
hsm_nibble/helpers.py
hsm_nibble/voronoi_centers.py
hsm_nibble-0.1.2.dist-info/METADATA
hsm_nibble-0.1.2.dist-info/WHEEL
hsm_nibble-0.1.2.dist-info/licenses/COPYING
hsm_nibble-0.1.2.dist-info/licenses/COPYING.LESSER
hsm_nibble-0.1.2.dist-info/licenses/LICENSE
hsm_nibble-0.1.2.dist-info/licenses/LICENSE.LESSER
hsm_nibble-0.1.2.dist-info/RECORD
