Metadata-Version: 2.1
Name: hsm_nibble
Version: 0.1.2
Summary: A library for generating HSM tool paths for CNC pocket milling.
Project-URL: Homepage, https://github.com/mrdunk/HSM_nibbler
Author-email: dunk <mrdunk@gmail.com>
License-File: COPYING
License-File: COPYING.LESSER
License-File: LICENSE
License-File: LICENSE.LESSER
Classifier: License :: OSI Approved :: GNU Affero General Public License v3
Classifier: Operating System :: OS Independent
Classifier: Programming Language :: Python :: 3
Classifier: Topic :: Scientific/Engineering
Requires-Python: >=3.7
